sn_demo/__init__.py
sn_demo/main.py
sn_demo-0.3.0.dist-info/entry_points.txt
sn_demo-0.3.0.dist-info/WHEEL
sn_demo-0.3.0.dist-info/METADATA
sn_demo-0.3.0.dist-info/RECORD
